{
	"format_version": "1.8.0",
	"animations": {
		"animation.baby_psycho_bear.Pose": {
			"loop": true,
			"bones": {
				"head": {
					"rotation": [7.5, 27.5, 0]
				},
				"left_arm": {
					"rotation": [-27.5, 0, 0]
				},
				"left_leg": {
					"rotation": [37.5, 0, 0]
				},
				"right_leg": {
					"rotation": [-10, 0, 0]
				},
				"right_arm": {
					"rotation": [30, 0, 0]
				},
				"behr": {
					"rotation": [0, -22.5, 0]
				},
				"tail": {
					"rotation": [-40, 0, 0]
				}
			}
		},
		"animation.baby_psycho_bear.idle": {
			"loop": true,
			"animation_length": 2,
			"bones": {
				"head": {
					"rotation": ["math.cos((query.anim_time -0.3)*180)*-2", 0, 0]
				},
				"torso": {
					"rotation": ["math.cos((query.anim_time -0.2)*180)*1", 0, 0],
					"position": [0, "-0.3+math.cos((query.anim_time -0.0)*180)*0.3", 0]
				},
				"tail": {
					"rotation": [-55, 0, 0]
				}
			}
		},
		"animation.baby_psycho_bear.walk": {
			"loop": true,
			"animation_length": 1.5,
			"bones": {
				"right_leg": {
					"rotation": ["math.cos((query.anim_time -0.1)*240)*-25", 0, 0],
					"position": [0, "1+math.cos((query.anim_time -0.2)*240)*-1", 0]
				},
				"left_leg": {
					"rotation": ["math.cos((query.anim_time -0.1)*240)*25", 0, 0],
					"position": [0, "1+math.cos((query.anim_time -0.2)*240)*1", 0]
				},
				"torso": {
					"rotation": ["math.cos((query.anim_time -0.2)*240)*3", 0, 0],
					"position": [0, "-0.3+math.cos((query.anim_time -0.0)*240)*0.3", 0]
				},
				"tail": {
					"rotation": ["-55+math.cos((query.anim_time -0.3)*240)*4", 0, 0]
				},
				"left_arm": {
					"rotation": ["math.cos((query.anim_time -0.0)*240)*-25", 0, 0],
					"position": [0, "1+math.cos((query.anim_time -0.2)*240)*-1", 0]
				},
				"right_arm": {
					"rotation": ["math.cos((query.anim_time -0.0)*240)*25", 0, 0],
					"position": [0, "1+math.cos((query.anim_time -0.2)*240)*1", 0]
				}
			}
		},
		"animation.baby_psycho_bear.sleep": {
			"loop": true,
			"animation_length": 2,
			"bones": {
				"behr": {
					"position": [0, -5, 0]
				},
				"right_leg": {
					"rotation": [-84.23137, 29.8742, 2.88066],
					"position": [-2, 2, 2]
				},
				"left_leg": {
					"rotation": [-84.23137, -29.8742, -2.88066],
					"position": [2, 2, 2]
				},
				"tail": {
					"rotation": [-57.5, 0, 0]
				},
				"head": {
					"rotation": ["27.5+math.cos((query.anim_time -0.0)*180)*2", 0, 0]
				},
				"left_arm": {
					"rotation": [-85, 0, 0],
					"position": [2, 2, 0]
				},
				"right_arm": {
					"rotation": [-85, 0, 0],
					"position": [-2, 2, 0]
				}
			}
		},
		"animation.baby_psycho_bear.back_scratch": {
			"loop": true,
			"animation_length": 0.5,
			"bones": {
				"body": {
					"rotation": [-90, 0, 0],
					"position": [0, "math.cos((query.anim_time -0.0)*720)*1", -5]
				},
				"tail": {
					"rotation": [-35, 0, 0]
				},
				"head": {
					"position": [0, 0, "math.cos((query.anim_time -0.1)*720)*0.5"]
				},
				"left_arm": {
					"rotation": [62.5, 15, 0]
				},
				"right_arm": {
					"rotation": [62.5, -15, 0]
				}
			}
		}
	}
}